fixedlength
